Lab_10/ejercicio1/EJER1.v
//Ejercicio 01
//Lab 10
//Jonathan Menendez 18023

//FliFlop tipo D para uso en fetch
module FFD4(
    input wire clk, reset, enable,
    input wire [3:0]D,
    output reg [3:0]Q);

    always @ (posedge clk or posedge reset) begin
        if (reset)
            Q <= 4'b0000;
        else if (enable)
            Q <= D;
    end
endmodule

//Modulo del counter de 12 bits
module counter(
    input wire clk, reset, enable, bitcar,
    input wire [11:0]L,
    output reg [11:0]E);

        always @ (posedge clk or posedge reset or posedge bitcar)begin
            if (reset == 1) // Empieza en 0
                E <= 12'b000000000000;

            else if(enable == 1) // Cada vez que pase el clock se le suma uno
                E <= E + 1;

            else if(bitcar == 1) // Mientras non sea 1, el valor va a ser el de load
                E <= L;
            end

endmodule

//Modulo de ROM para la memoria "memory.jmc"
module rom(
    input wire[11:0]Lect,
    output wire [7:0]Data);

        reg [7:0] Memory[0:4095]; // Tamaño de nuestra memoria

        initial begin
            $readmemb("memory.jmc", Memory); //llamar a nuestro archivo de datos
        end

        assign Data = Memory[Lect];
endmodule

//modulo fetch (FlipFlop de 8 bits) utilizando el de 4 bits para salidas
module fetch(
    input wire clk, reset, enable2,
    input wire [7:0]D8,
    output wire [3:0]Q1,
    output wire [3:0]Q2);  //dos salidas de 4

        FFD4 u1(clk, reset, enable2, D8[7:4], Q1);
        FFD4 u2(clk, reset, enable2, D8[3:0], Q2);
endmodule

//modulo de union de todos los modulos anteriores.
module main(
    input wire clk, reset, enable, non, enable2,
    input wire [11:0]L,
    output wire [7:0]Pb,
    output wire [3:0]Q1,
    output wire [3:0]Q2);

        wire [11:0]C;

        counter u1(clk, reset, enable, bitcar, L, C);
        rom u2(C, Pb);
        fetch u3(clk, reset, enable2, Pb, Q1, Q2);
endmodule

Lab_10/ejercicio1/EJER1_tb.v
//testbench EJER1
//Jonathan Menendez 18023

module testbench();

//llamar todos los dato que se quieren evaluar
reg clk, reset, enable, enable2, bitcar;
reg [11:0]L;
wire [3:0]Q1;
wire [3:0]Q2;
wire [7:0]Pb;

main u1(clk, reset, enable, bitcar, enable2, L, Pb, Q1, Q2);

//clock y muestras de datos
always
    #1 clk = ~clk;
initial begin
    #1
    $display("------------------------------------------------------------");
    $display("clk  |  reset  |  enable  |  bitcar  |  enable2  |   L  ||  Pb |  Q1  |  Q2");
    $display("--------------------------------------------------------||------------");
    $monitor("   %b     %b     %b     %b     %b     %b    ||     %b     %b    %b  ", clk, reset, enable, bitcar, enable2, L, Pb, Q1, Q2);
    clk = 0; reset = 0; enable = 0; enable2 = 0; bitcar = 0; L = 12'b000000000000;
    #2 reset = 1;
    #2 reset = 0;
    #2 enable = 1;
    #2 enable2 = 1;
    #2 bitcar = 1;
    #2 L = 12'b000000000001;
    #2 L = 12'b000000001010;
    #2 bitcar = 0;
    #2 bitcar = 1;
    #2 enable = 1; L = 12'b000111001010;
    #2 enable2 = 1; L = 12'b110001001010;
end

initial
  #25 $finish;

//instruccion para GTKWave
initial begin
  $dumpfile("EJER1_tb.vcd");
  $dumpvars(0, testbench);
end

endmodule

Lab_10/ejercicio1/EJER1_tb.vcd
$date
	Sat Nov 07 18:26:16 2020
$end
$version
	Icarus Verilog
$end
$timescale
	1ps
$end
$scope module testbench $end
$var wire 4 ! Q2 [3:0] $end
$var wire 4 " Q1 [3:0] $end
$var wire 8 # Pb [7:0] $end
$var reg 12 $ L [11:0] $end
$var reg 1 % bitcar $end
$var reg 1 & clk $end
$var reg 1 ' enable $end
$var reg 1 ( enable2 $end
$var reg 1 ) reset $end
$scope module u1 $end
$var wire 12 * L [11:0] $end
$var wire 1 + bitcar $end
$var wire 1 & clk $end
$var wire 1 ' enable $end
$var wire 1 ( enable2 $end
$var wire 1 % non $end
$var wire 1 ) reset $end
$var wire 4 , Q2 [3:0] $end
$var wire 4 - Q1 [3:0] $end
$var wire 8 . Pb [7:0] $end
$var wire 12 / C [11:0] $end
$scope module u1 $end
$var wire 12 0 L [11:0] $end
$var wire 1 + bitcar $end
$var wire 1 & clk $end
$var wire 1 ' enable $end
$var wire 1 ) reset $end
$var reg 12 1 E [11:0] $end
$upscope $end
$scope module u2 $end
$var wire 8 2 Data [7:0] $end
$var wire 12 3 Lect [11:0] $end
$upscope $end
$scope module u3 $end
$var wire 8 4 D8 [7:0] $end
$var wire 1 & clk $end
$var wire 1 ( enable2 $end
$var wire 1 ) reset $end
$var wire 4 5 Q2 [3:0] $end
$var wire 4 6 Q1 [3:0] $end
$scope module u1 $end
$var wire 4 7 D [3:0] $end
$var wire 1 & clk $end
$var wire 1 ( enable $end
$var wire 1 ) reset $end
$var reg 4 8 Q [3:0] $end
$upscope $end
$scope module u2 $end
$var wire 4 9 D [3:0] $end
$var wire 1 & clk $end
$var wire 1 ( enable $end
$var wire 1 ) reset $end
$var reg 4 : Q [3:0] $end
$upscope $end
$upscope $end
$upscope $end
$upscope $end
$enddefinitions $end
#0
$dumpvars
bx :
bx 9
bx 8
bx 7
bx 6
bx 5
bx 4
bx 3
bx 2
bx 1
bx 0
bx /
bx .
bx -
bx ,
z+
bx *
x)
x(
x'
x&
x%
bx $
bx #
bx "
bx !
$end
#1
b0 $
b0 *
b0 0
0%
0(
0'
0)
0&
#2
1&
#3
b0 7
b0 9
b0 #
b0 .
b0 2
b0 4
b0 /
b0 1
b0 3
b0 !
b0 ,
b0 5
b0 :
b0 "
b0 -
b0 6
b0 8
0&
1)
#4
1&
#5
0&
0)
#6
1&
#7
0&
1'
#8
b101 9
b101 #
b101 .
b101 2
b101 4
b1 /
b1 1
b1 3
1&
#9
0&
1(
#10
b101 7
b0 9
b1010000 #
b1010000 .
b1010000 2
b1010000 4
b10 /
b10 1
b10 3
b101 !
b101 ,
b101 5
b101 :
1&
#11
0&
1%
#12
b1010 7
b101 9
b10100101 #
b10100101 .
b10100101 2
b10100101 4
b11 /
b11 1
b11 3
b101 "
b101 -
b101 6
b101 8
b0 !
b0 ,
b0 5
b0 :
1&
#13
0&
b1 $
b1 *
b1 0
#14
b1100 7
b11 9
b11000011 #
b11000011 .
b11000011 2
b11000011 4
b100 /
b100 1
b100 3
b101 !
b101 ,
b101 5
b101 :
b1010 "
b1010 -
b1010 6
b1010 8
1&
#15
0&
b1010 $
b1010 *
b1010 0
#16
b1110 7
b1 9
b11100001 #
b11100001 .
b11100001 2
b11100001 4
b101 /
b101 1
b101 3
b1100 "
b1100 -
b1100 6
b1100 8
b11 !
b11 ,
b11 5
b11 :
1&
#17
0&
0%
#18
b1001 7
b1111 9
b10011111 #
b10011111 .
b10011111 2
b10011111 4
b110 /
b110 1
b110 3
b1 !
b1 ,
b1 5
b1 :
b1110 "
b1110 -
b1110 6
b1110 8
1&
#19
0&
1%
#20
b1111 7
b0 9
b11110000 #
b11110000 .
b11110000 2
b11110000 4
b111 /
b111 1
b111 3
b1001 "
b1001 -
b1001 6
b1001 8
b1111 !
b1111 ,
b1111 5
b1111 :
1&
#21
0&
b111001010 $
b111001010 *
b111001010 0
#22
b1010 7
b1111 9
b10101111 #
b10101111 .
b10101111 2
b10101111 4
b1000 /
b1000 1
b1000 3
b0 !
b0 ,
b0 5
b0 :
b1111 "
b1111 -
b1111 6
b1111 8
1&
#23
0&
b110001001010 $
b110001001010 *
b110001001010 0
#24
b0 7
b1111 #
b1111 .
b1111 2
b1111 4
b1001 /
b1001 1
b1001 3
b1010 "
b1010 -
b1010 6
b1010 8
b1111 !
b1111 ,
b1111 5
b1111 :
1&
