Lab_10/ejercicio2/ALU.v
//Ejercicio 2
//ALU
//Jonathan Menendez 18023

//modulo del FlipFlop tipo D
module FFD4(
    input wire clk, reset, enable,
    input wire [3:0]D,
    output reg [3:0]Q);

    always @ (posedge clk or posedge reset) begin
        if (reset)
            Q <= 4'b0000;
        else if (enable)
            Q <= D;
    end
endmodule

//modulo del Buffer Tri estado
module BufferTri(
    input wire enable,
    input wire [3:0]In,
    output wire [3:0]Ex);

        assign Ex = (enable) ? In:4'bz;
endmodule

//modulo de ALU utilizado
module ALU(
    input wire [3:0]A,
    input wire [3:0]B,
    input wire [2:0]Com, // intrucciones de la ALU
    output reg [3:0]Res, //Resultados de las intrucciones
    output reg Carry,
    output reg Exit);

        reg [4:0]k; //Registro interno

        always @ (A or B or Com) begin

            case(Com)   //case para dar instrucion a cada caso del reg k

                3'b000: begin
                            //pasa A
                            k = 5'b00000;
                            k = A;
                            Carry = 1'b0;
                            Exit = (k == 5'b00000) ? 1:0;
                            Res = k[3:0];
                        end

                3'b001: begin
                            // Comparador
                            k[4:0] = 5'b00000;
                            k = A - B;
                            Carry = (k[4] == 5'b00000) ? 1:0;
                            Exit = (k == 5'b00000) ? 1:0;
                            Res = k[3:0];
                        end

                3'b010: begin
                            // pasa B
                            k[4:0] = 5'b00000;
                            k = B;
                            Carry = 1'b0;
                            Exit = (k == 5'b00000) ? 1:0;
                            Res = k[3:0];
                        end

                3'b011: begin
                            // suma
                            k[4:0] = 5'b00000;
                            k = A + B;
                            Carry = (k[4] == 5'b00000) ? 1:0;
                            Exit = (k == 5'b00000) ? 1:0;
                            Res = k[3:0];
                        end

                3'b100: begin
                            //NAND
                            k = 5'b00000;
                            k = ~(A & B);
                            Carry = 1'b0;
                            Exit = (k == 5'b00000) ? 1:0;
                            Res = k[3:0];
                        end
            endcase
        end
endmodule

//modulo de union de todos los modulos anteriores
module main(
    input wire [3:0]In,
    input wire enable, enable1, enable2, clk, reset,
    input wire [2:0]Com,
    output wire Carry, Exit,
    output wire [3:0]S);

        wire [3:0]a;
        wire [3:0]b;
        wire [3:0]alu_out;

        BufferTri u1(In, enable1, b);
        FFD4 u2(clk, reset, enable, alu_out, a);
        ALU u4(a, b, Com, alu_out, Carry, Exit);
        BufferTri u3(alu_out, enable2, S);

endmodule

Lab_10/ejercicio2/ALU_tb.v
//Ejercicio 2
//ALU_tb
//Jonathan Menendez 18023

module testbench();

reg [3:0]In;
reg enable1, clk, reset, enable, enable2;
reg [2:0]Com;
wire Carry, Exit;
wire [3:0]S;

//llamada al modulo principal
main u1(In, enable1, clk, reset, enable, enable2, Com, Carry, Exit, S);

always
    #1 clk = ~clk;

initial begin
    #1
    $display("-----------------------------------------------------------------------------");
    $display("| clk | enable |  In  | reset | enable1 | enable2 | Com || Carry | Exit | S |");
    $display("--------------------------------------------------------||------------");
    $monitor("|   %b     %b      %b     %b        %b      %b      %b    ||   %b    %b    %b  |", clk, enable, In, reset, enable1, enable2, Com, Carry, Exit, S);
    clk = 0; enable = 0; In = 4'b0000; reset = 0; enable1 = 0; enable2 = 0; Com = 3'b000;
    #2 reset = 1;
    #2 reset = 0;
    #2 In = 4'b0001; enable1 = 1;
    #2 enable = 1; enable2 = 1; Com = 3'b010;

end

initial
    #40 $finish;

initial begin
    $dumpfile("ALU_tb.vcd");
    $dumpvars(0, testbench);
end

endmodule

Lab_10/ejercicio2/ALU_tb.vcd
$date
	Sat Nov 07 20:24:45 2020
$end
$version
	Icarus Verilog
$end
$timescale
	1ps
$end
$scope module testbench $end
$var wire 4 ! S [3:0] $end
$var wire 1 " Exit $end
$var wire 1 # Carry $end
$var reg 3 $ Com [2:0] $end
$var reg 4 % In [3:0] $end
$var reg 1 & clk $end
$var reg 1 ' enable $end
$var reg 1 ( enable1 $end
$var reg 1 ) enable2 $end
$var reg 1 * reset $end
$scope module u1 $end
$var wire 3 + Com [2:0] $end
$var wire 4 , In [3:0] $end
$var wire 1 ' clk $end
$var wire 1 ( enable $end
$var wire 1 & enable1 $end
$var wire 1 * enable2 $end
$var wire 1 ) reset $end
$var wire 4 - b [3:0] $end
$var wire 4 . alu_out [3:0] $end
$var wire 4 / a [3:0] $end
$var wire 4 0 S [3:0] $end
$var wire 1 " Exit $end
$var wire 1 # Carry $end
$scope module u1 $end
$var wire 4 1 In [3:0] $end
$var wire 1 2 enable $end
$var wire 4 3 Ex [3:0] $end
$upscope $end
$scope module u2 $end
$var wire 1 ' clk $end
$var wire 1 ( enable $end
$var wire 1 ) reset $end
$var wire 4 4 D [3:0] $end
$var reg 4 5 Q [3:0] $end
$upscope $end
$scope module u3 $end
$var wire 4 6 In [3:0] $end
$var wire 1 7 enable $end
$var wire 4 8 Ex [3:0] $end
$upscope $end
$scope module u4 $end
$var wire 4 9 A [3:0] $end
$var wire 4 : B [3:0] $end
$var wire 3 ; Com [2:0] $end
$var reg 1 # Carry $end
$var reg 1 " Exit $end
$var reg 4 < Res [3:0] $end
$var reg 5 = k [4:0] $end
$upscope $end
$upscope $end
$upscope $end
$enddefinitions $end
#0
$dumpvars
bx =
bx <
bx ;
bx :
bx 9
bx 8
x7
b0x 6
bx 5
bx 4
bx 3
x2
b0x 1
bx 0
bx /
bx .
bx -
bx ,
bx +
x*
x)
x(
x'
x&
bx %
bx $
x#
x"
bx !
$end
#1
bz -
bz 3
bz :
0#
b0xxxx =
02
b0 $
b0 +
b0 ;
0)
0(
b0 6
0*
b0 %
b0 ,
0'
b0 1
0&
#2
b1 1
1&
#3
b0 1
0&
b1 6
1*
#4
b1 1
1&
#5
b0 1
0&
b0 6
0*
#6
b1 1
1&
#7
b0xxxx =
b0 -
b0 3
b0 :
12
b0 1
0&
1(
b1 %
b1 ,
#8
b0xxxx =
b1 -
b1 3
b1 :
b1 1
1&
#9
b0 /
b0 5
b0 9
bz !
bz 0
bz 8
07
b0 -
b0 3
b0 :
b0 .
b0 4
b0 <
1"
b0 =
b0 1
0&
b10 $
b10 +
b10 ;
1)
1'
#10
b0 !
b0 0
b0 8
17
b1 .
b1 4
b1 <
0"
b1 =
b1 -
b1 3
b1 :
b1 1
1&
#11
bz !
bz 0
bz 8
07
b0 .
b0 4
b0 <
1"
b0 =
b0 -
b0 3
b0 :
b0 1
0&
#12
b0 !
b0 0
b0 8
17
b1 .
b1 4
b1 <
0"
b1 =
b1 -
b1 3
b1 :
b1 1
1&
#13
bz !
bz 0
bz 8
07
b0 .
b0 4
b0 <
1"
b0 =
b0 -
b0 3
b0 :
b0 1
0&
#14
b0 !
b0 0
b0 8
17
b1 .
b1 4
b1 <
0"
b1 =
b1 -
b1 3
b1 :
b1 1
1&
#15
bz !
bz 0
bz 8
07
b0 .
b0 4
b0 <
1"
b0 =
b0 -
b0 3
b0 :
b0 1
0&
#16
b0 !
b0 0
b0 8
17
b1 .
b1 4
b1 <
0"
b1 =
b1 -
b1 3
b1 :
b1 1
1&
#17
bz !
bz 0
bz 8
07
b0 .
b0 4
b0 <
1"
b0 =
b0 -
b0 3
b0 :
b0 1
0&
#18
b0 !
b0 0
b0 8
17
b1 .
b1 4
b1 <
0"
b1 =
b1 -
b1 3
b1 :
b1 1
1&
#19
bz !
bz 0
bz 8
07
b0 .
b0 4
b0 <
1"
b0 =
b0 -
b0 3
b0 :
b0 1
0&
#20
b0 !
b0 0
b0 8
17
b1 .
b1 4
b1 <
0"
b1 =
b1 -
b1 3
b1 :
b1 1
1&
#21
bz !
bz 0
bz 8
07
b0 .
b0 4
b0 <
1"
b0 =
b0 -
b0 3
b0 :
b0 1
0&
#22
b0 !
b0 0
b0 8
17
b1 .
b1 4
b1 <
0"
b1 =
b1 -
b1 3
b1 :
b1 1
1&
#23
bz !
bz 0
bz 8
07
b0 .
b0 4
b0 <
1"
b0 =
b0 -
b0 3
b0 :
b0 1
0&
#24
b0 !
b0 0
b0 8
17
b1 .
b1 4
b1 <
0"
b1 =
b1 -
b1 3
b1 :
b1 1
1&
#25
bz !
bz 0
bz 8
07
b0 .
b0 4
b0 <
1"
b0 =
b0 -
b0 3
b0 :
b0 1
0&
#26
b0 !
b0 0
b0 8
17
b1 .
b1 4
b1 <
0"
b1 =
b1 -
b1 3
b1 :
b1 1
1&
#27
bz !
bz 0
bz 8
07
b0 .
b0 4
b0 <
1"
b0 =
b0 -
b0 3
b0 :
b0 1
0&
#28
b0 !
b0 0
b0 8
17
b1 .
b1 4
b1 <
0"
b1 =
b1 -
b1 3
b1 :
b1 1
1&
#29
bz !
bz 0
bz 8
07
b0 .
b0 4
b0 <
1"
b0 =
b0 -
b0 3
b0 :
b0 1
0&
#30
b0 !
b0 0
b0 8
17
b1 .
b1 4
b1 <
0"
b1 =
b1 -
b1 3
b1 :
b1 1
1&
#31
bz !
bz 0
bz 8
07
b0 .
b0 4
b0 <
1"
b0 =
b0 -
b0 3
b0 :
b0 1
0&
#32
b0 !
b0 0
b0 8
17
b1 .
b1 4
b1 <
0"
b1 =
b1 -
b1 3
b1 :
b1 1
1&
#33
bz !
bz 0
bz 8
07
b0 .
b0 4
b0 <
1"
b0 =
b0 -
b0 3
b0 :
b0 1
0&
#34
b0 !
b0 0
b0 8
17
b1 .
b1 4
b1 <
0"
b1 =
b1 -
b1 3
b1 :
b1 1
1&
#35
bz !
bz 0
bz 8
07
b0 .
b0 4
b0 <
1"
b0 =
b0 -
b0 3
b0 :
b0 1
0&
#36
b0 !
b0 0
b0 8
17
b1 .
b1 4
b1 <
0"
b1 =
b1 -
b1 3
b1 :
b1 1
1&
#37
bz !
bz 0
bz 8
07
b0 .
b0 4
b0 <
1"
b0 =
b0 -
b0 3
b0 :
b0 1
0&
#38
b0 !
b0 0
b0 8
17
b1 .
b1 4
b1 <
0"
b1 =
b1 -
b1 3
b1 :
b1 1
1&
#39
bz !
bz 0
bz 8
07
b0 .
b0 4
b0 <
1"
b0 =
b0 -
b0 3
b0 :
b0 1
0&
#40
b0 !
b0 0
b0 8
17
b1 .
b1 4
b1 <
0"
b1 =
b1 -
b1 3
b1 :
b1 1
1&
